annotated_fastapi_router/__init__.py
annotated_fastapi_router/error.py
annotated_fastapi_router/routing.py
annotated_fastapi_router/types.py
annotated_fastapi_router-0.1.0.dist-info/LICENSE
annotated_fastapi_router-0.1.0.dist-info/METADATA
annotated_fastapi_router-0.1.0.dist-info/WHEEL
annotated_fastapi_router-0.1.0.dist-info/entry_points.txt
annotated_fastapi_router-0.1.0.dist-info/RECORD
