Metadata-Version: 2.1
Name: annotated_fastapi_router
Version: 0.1.0
Summary: FastAPI annotated api routed
Home-page: https://github.com/feodor-ra/annotated-fastapi-router
License: MIT
Keywords: annotated,fastapi
Author: Fedor Ratschew
Author-email: feodor.ra@me.com
Requires-Python: >=3.11,<4.0
Classifier: Development Status :: 5 - Production/Stable
Classifier: Framework :: FastAPI
Classifier: Intended Audience :: Developers
Classifier: License :: OSI Approved :: MIT License
Classifier: Programming Language :: Python :: 3
Classifier: Programming Language :: Python :: 3.11
Classifier: Programming Language :: Python :: 3.12
Classifier: Topic :: Software Development :: Libraries :: Python Modules
Classifier: Topic :: Utilities
Requires-Dist: fastapi (>=0.100.0)
Requires-Dist: pyhumps (>=3.8.0,<4.0.0)
Project-URL: Repository, https://github.com/feodor-ra/annotated-fastapi-router
